nestwork/__init__.py
nestwork/colonel/__init__.py
nestwork/gpm/README.md
nestwork/gpm/__init__.py
nestwork/gpm/main.py
nestwork/gpt/__init__.py
nestwork/gpt/rnn.torch.py
nestwork/gpt/sat.keras.ipynb
nestwork/gpt/sat.keras.py
nestwork/gpt/sat.tensorflow.py
nestwork/gpt/sat.torch.py
nestwork/makemore/.old/mlp.batch.tensorflow.py
nestwork/makemore/.old/mlp.regularization.tensorflow.py
nestwork/makemore/.old/mlp.viz.tensorflow.py
nestwork/makemore/__init__.py
nestwork/makemore/cnn.keras.py
nestwork/makemore/cnn.tensorflow.py
nestwork/makemore/cnn.torch.py
nestwork/makemore/mlp.keras.py
nestwork/makemore/mlp.tensorflow.py
nestwork/sold/__init__.py
nestwork/sold/bytecode.py
nestwork/sold/main.keras.py
nestwork/sold/solidity.py
nestwork/tokun/__init__.py
nestwork/tokun/data.py
nestwork/tokun/evaluation.py
nestwork/tokun/huggingface.py
nestwork/tokun/layers.py
nestwork/tokun/losses.py
nestwork/tokun/meta.py
nestwork/tokun/metrics.py
nestwork/tokun/model.py
nestwork/tokun/pipeline.py
nestwork-0.5.4.dist-info/METADATA
nestwork-0.5.4.dist-info/WHEEL
nestwork-0.5.4.dist-info/RECORD
